magic_api_mcp_server_fastmcp-0.1.7.dist-info/licenses/LICENSE
magicapi_mcp/__init__.py
magicapi_mcp/magicapi_assistant.py
magicapi_mcp/settings.py
magicapi_mcp/tool_composer.py
magicapi_mcp/tool_registry.py
magicapi_tools/__init__.py
magicapi_tools/logging_config.py
magicapi_tools/domain/__init__.py
magicapi_tools/domain/dtos/__init__.py
magicapi_tools/domain/dtos/api_dtos.py
magicapi_tools/domain/dtos/backup_dtos.py
magicapi_tools/domain/dtos/class_method_dtos.py
magicapi_tools/domain/dtos/debug_dtos.py
magicapi_tools/domain/dtos/query_dtos.py
magicapi_tools/domain/dtos/resource_dtos.py
magicapi_tools/domain/models/base_model.py
magicapi_tools/services/__init__.py
magicapi_tools/services/api_service.py
magicapi_tools/services/backup_service.py
magicapi_tools/services/base_service.py
magicapi_tools/services/class_method_service.py
magicapi_tools/services/debug_service.py
magicapi_tools/services/query_service.py
magicapi_tools/services/resource_service.py
magicapi_tools/tools/__init__.py
magicapi_tools/tools/api.py
magicapi_tools/tools/backup.py
magicapi_tools/tools/class_method.py
magicapi_tools/tools/code_generation.py
magicapi_tools/tools/common.py
magicapi_tools/tools/debug_api.py
magicapi_tools/tools/documentation.py
magicapi_tools/tools/query.py
magicapi_tools/tools/resource.py
magicapi_tools/tools/search.py
magicapi_tools/tools/system.py
magicapi_tools/utils/__init__.py
magicapi_tools/utils/extractor.py
magicapi_tools/utils/http_client.py
magicapi_tools/utils/kb_config.py
magicapi_tools/utils/kb_examples.py
magicapi_tools/utils/kb_extensions.py
magicapi_tools/utils/kb_functions.py
magicapi_tools/utils/kb_modules.py
magicapi_tools/utils/kb_plugins.py
magicapi_tools/utils/kb_practices.py
magicapi_tools/utils/kb_syntax.py
magicapi_tools/utils/kb_web_docs.py
magicapi_tools/utils/knowledge_base.py
magicapi_tools/utils/resource_manager.py
magicapi_tools/utils/response.py
magicapi_tools/utils/tool_helpers.py
magicapi_tools/utils/ws.py
magicapi_tools/ws/__init__.py
magicapi_tools/ws/client.py
magicapi_tools/ws/debug_service.py
magic_api_mcp_server_fastmcp-0.1.7.dist-info/METADATA
magic_api_mcp_server_fastmcp-0.1.7.dist-info/WHEEL
magic_api_mcp_server_fastmcp-0.1.7.dist-info/entry_points.txt
magic_api_mcp_server_fastmcp-0.1.7.dist-info/top_level.txt
magic_api_mcp_server_fastmcp-0.1.7.dist-info/RECORD
